dash_devices/__init__.py
dash_devices/_callback_context.py
dash_devices/_configs.py
dash_devices/_utils.py
dash_devices/_validate.py
dash_devices/_watch.py
dash_devices/dash.py
dash_devices/dash_renderer.dev.js
dash_devices/dash_renderer.min.js
dash_devices/dependencies.py
dash_devices/exceptions.py
dash_devices/extract-meta.js
dash_devices/fingerprint.py
dash_devices/pusher.py
dash_devices/resources.py
dash_devices/version.py
dash_devices/development/__init__.py
dash_devices/development/_all_keywords.py
dash_devices/development/_py_components_generation.py
dash_devices/development/_r_components_generation.py
dash_devices/development/base_component.py
dash_devices/development/build_process.py
dash_devices/development/component_generator.py
dash_devices/development/component_loader.py
dash_devices/testing/__init__.py
dash_devices/testing/application_runners.py
dash_devices/testing/browser.py
dash_devices/testing/composite.py
dash_devices/testing/consts.py
dash_devices/testing/dash_page.py
dash_devices/testing/errors.py
dash_devices/testing/newhooks.py
dash_devices/testing/plugin.py
dash_devices/testing/wait.py
dash_devices-0.1.3.dist-info/LICENSE
dash_devices-0.1.3.dist-info/METADATA
dash_devices-0.1.3.dist-info/WHEEL
dash_devices-0.1.3.dist-info/top_level.txt
dash_devices-0.1.3.dist-info/RECORD
