Metadata-Version: 2.1
Name: dash-devices
Version: 0.1.3
Summary: Dash for devices.
Home-page: https://github.com/richlegrand/dash_devices
Author: Charmed Labs
Author-email: support@charmedlabs.com
License: UNKNOWN
Platform: UNKNOWN
Classifier: Programming Language :: Python :: 3
Classifier: License :: OSI Approved :: MIT License
Classifier: Operating System :: OS Independent
Requires-Python: >=3.7
